CatKit_utils-0.0.2.dist-info/METADATA
CatKit_utils-0.0.2.dist-info/RECORD
CatKit_utils-0.0.2.dist-info/WHEEL
CatKit_utils-0.0.2.dist-info/top_level.txt
ckutil/__init__.py
ckutil/rdk.py
